<?xml version="1.0" encoding="utf-8"?>
<data bg_color="16777215" pattern_url="backgrounds/50.png">
  <item type="text" index="0" font="ChunkFive Roman" size="68" color="16538936@@@16538936@@@16538936@@@16538936@@@16538936@@@16538936" xpos="29" ypos="322.4" alignment="center" rotation="0" scalex="0.8101701736450195" scaley="0.8101701736450195" filter="true"><![CDATA[ONLINE]]></item>
  <item type="text" index="1" font="ChunkFive Roman" size="68" color="102849@@@102849@@@102849@@@102849@@@102849@@@102849@@@102849@@@102849@@@102849@@@102849@@@102849" xpos="36.4" ypos="193.35" alignment="center" rotation="0" scalex="0.46138572692871094" scaley="0.46138572692871094" filter="true"><![CDATA[QUICK GUIDE]]></item>
  <item type="shape" index="2" shape_type="Rectangle" color="159685 " xpos="-30" ypos="37" width="446" height="44" rotation="0"/>
  <item type="text" index="3" font="Bitter" size="25" color="16777215@@@16777215@@@16777215@@@16777215@@@16777215@@@16777215@@@16777215@@@16777215@@@16777215@@@16777215@@@16777215@@@16777215@@@16777215@@@16777215@@@16777215@@@16777215@@@16777215@@@16777215@@@16777215@@@16777215@@@16777215@@@16777215@@@16777215@@@16777215@@@16777215@@@16777215@@@16777215@@@16777215@@@16777215@@@16777215@@@16777215@@@16777215@@@16777215@@@16777215@@@16777215@@@16777215@@@16777215" xpos="12" ypos="48.6" alignment="center" rotation="0" scalex="0.578277587890625" scaley="0.578277587890625" filter="true"><![CDATA[Instant EBook Presence & Pulse Mascot]]></item>
  <item type="shape" index="4" shape_type="Rectangle" color="159685 " xpos="-6" ypos="85" width="446" height="6" rotation="0"/>
  <item type="shape" index="5" shape_type="Rectangle" color="159685 " xpos="-6" ypos="25.95" width="446" height="6" rotation="0"/>
  <item type="image" index="6" source="assets/images/seals/seal5.png" xpos="291" ypos="4.75" width="121" height="112.8" rotation="0"/>
  <item type="text" index="7" font="Impact" size="25" color="16189952@@@16189952@@@16189952@@@16189952" xpos="329.25" ypos="42" alignment="center" rotation="0" scalex="0.796807050704956" scaley="0.796807050704956" filter="true"><![CDATA[BEST]]></item>
  <item type="text" index="8" font="ChunkFive Roman" size="68" color="102849@@@102849@@@102849@@@102849@@@102849@@@102849@@@102849@@@102849" xpos="33.6" ypos="219.8" alignment="center" rotation="0" scalex="0.6095036864280701" scaley="0.6095036864280701" filter="true"><![CDATA[TO BOOST]]></item>
  <item type="text" index="9" font="Impact" size="25" color="16258304@@@16258304@@@16258304@@@16258304@@@16258304@@@16258304" xpos="319" ypos="60" alignment="left" rotation="0" scalex="0.9623260498046875" scaley="0.9623260498046875" filter="true"><![CDATA[SELLER]]></item>
  <item type="image" index="10" source="assets/images/others/56.png" xpos="393.8" ypos="277.8" width="80.25" height="117.85" rotation="180"/>
  <item type="image" index="11" source="uploaded_image/52793464a82d9.png" xpos="246.2" ypos="150.35" width="111.5" height="257.9" rotation="0"/>
  <item type="text" index="12" font="ChunkFive Roman" size="68" color="102849@@@102849@@@102849@@@102849@@@102849@@@102849@@@102849@@@102849@@@102849@@@102849" xpos="36.6" ypos="259.4" alignment="center" rotation="0" scalex="0.4871905446052551" scaley="0.4871905446052551" filter="true"><![CDATA[YOUR SALES]]></item>
  <item type="text" index="13" font="ChunkFive Roman" size="68" color="16538936@@@16538936@@@16538936@@@16538936@@@16538936@@@16538936@@@16538936" xpos="34.6" ypos="288.2" alignment="center" rotation="0" scalex="0.6194031834602356" scaley="0.6194031834602356" filter="true"><![CDATA[THROUGH]]></item>
</data>