<?xml version="1.0" encoding="utf-8"?>
<data bg_color="0xffffff" pattern_url="backgrounds/33.png">
  <item type="image" index="0" source="assets/images/lights/smoothlight.png" xpos="-84.5" ypos="-61.8" width="582" height="581" rotation="0"/>
  <item type="text" index="1" font="ChunkFive Roman" size="68" color="15891716" xpos="18.85" ypos="-0.9" alignment="left" rotation="0" scalex="2.1946380138397217" scaley="2.1946380138397217"><![CDATA[7]]></item>
  <item type="text" index="2" font="Myriad Pro Cond" size="25" color="14921219@@@14921219@@@14921219@@@14921219@@@14921219@@@14921219@@@14921219@@@14921219@@@14921219" xpos="10.2" ypos="351.8" alignment="center" rotation="0" scalex="2.0830137729644775" scaley="2.0830137729644775"><![CDATA[JOHN CRUZ]]></item>
  <item type="text" index="3" font="BlackJack" size="13" color="9503490@@@9503490@@@9503490@@@9503490@@@9503490@@@9503490@@@9503490@@@9503490@@@9503490@@@9503490@@@9503490@@@9503490@@@9503490@@@9503490@@@9503490@@@9503490@@@9503490@@@9503490@@@9503490@@@9503490@@@9503490@@@9503490@@@9503490@@@9503490@@@9503490@@@9503490@@@9503490@@@9503490@@@9503490@@@9503490@@@9503490@@@9503490@@@9503490@@@9503490@@@9503490@@@9503490@@@9503490@@@9503490" xpos="16.35" ypos="248.85" alignment="left" rotation="0" scalex="1.7357025146484375" scaley="1.7357025146484375"><![CDATA[Compliments of Retail Growth Solutions]]></item>
  <item type="text" index="4" font="ChunkFive Roman" size="68" color="0@@@0@@@0@@@0@@@0@@@0@@@0" xpos="111.35" ypos="53.15" alignment="left" rotation="0" scalex="0.6775142550468445" scaley="0.6775142550468445"><![CDATA[TIPS TO]]></item>
  <item type="text" index="5" font="ChunkFive Roman" size="68" color="0@@@0@@@0@@@0@@@0@@@0@@@0@@@0@@@0@@@0@@@0" xpos="18.4" ypos="137.45" alignment="left" rotation="0" scalex="0.7220047116279602" scaley="0.7454709410667419"><![CDATA[YOUR RETAIL]]></item>
  <item type="text" index="6" font="ChunkFive Roman" size="68" color="0@@@0@@@0@@@0@@@0@@@0@@@0@@@0" xpos="99.95" ypos="95.65" alignment="left" rotation="0" scalex="0.6617493629455566" scaley="0.6901490688323975"><![CDATA[MAXIMIZE]]></item>
  <item type="text" index="7" font="ChunkFive Roman" size="68" color="0@@@0@@@0@@@0@@@0@@@0@@@0" xpos="17.45" ypos="178.15" alignment="left" rotation="0" scalex="1.1199760437011719" scaley="1.1199760437011719"><![CDATA[PROFITS]]></item>
  <item type="text" index="8" font="Mako" size="25" color="13279744@@@13279744@@@13279744@@@13279744@@@13279744@@@13279744" xpos="18.6" ypos="404.75" alignment="left" rotation="0" scalex="0.9740752577781677" scaley="0.9740752577781677"><![CDATA[AUTHOR]]></item>
  <item type="text" index="9" font="ChunkFive Roman" size="68" color="0" xpos="350.45" ypos="403.85" alignment="left" rotation="21.534360896254853" scalex="0.9964005059876697" scaley="0.9964005059876697"><![CDATA[1]]></item>
  <item type="text" index="10" font="ChunkFive Roman" size="68" color="0" xpos="289.5" ypos="428.4" alignment="left" rotation="0" scalex="1" scaley="1"><![CDATA[2]]></item>
  <item type="text" index="11" font="ChunkFive Roman" size="68" color="0" xpos="366.35" ypos="425.45" alignment="left" rotation="0" scalex="1" scaley="1"><![CDATA[3]]></item>
  <item type="text" index="12" font="ChunkFive Roman" size="68" color="0" xpos="243.85" ypos="477.25" alignment="left" rotation="-17.522180103620222" scalex="0.9971492114500993" scaley="0.9971492114500993"><![CDATA[4]]></item>
  <item type="text" index="13" font="ChunkFive Roman" size="68" color="0" xpos="329.95" ypos="463.4" alignment="left" rotation="0" scalex="1" scaley="1"><![CDATA[5]]></item>
  <item type="text" index="14" font="ChunkFive Roman" size="68" color="0" xpos="373.4" ypos="487.45" alignment="left" rotation="0" scalex="0.7400317192077637" scaley="0.7400317192077637"><![CDATA[6]]></item>
  <item type="text" index="15" font="ChunkFive Roman" size="68" color="0" xpos="298.85" ypos="483.4" alignment="left" rotation="0" scalex="0.8525121808052063" scaley="0.8525121808052063"><![CDATA[7]]></item>
</data>